AUTHORS
BUGS.md
CHANGES.rst
LICENSE
MANIFEST.in
README.rst
TODO.md
setup.py
hhunt/__init__.py
hhunt.egg-info/PKG-INFO
hhunt.egg-info/SOURCES.txt
hhunt.egg-info/dependency_links.txt
hhunt.egg-info/entry_points.txt
hhunt.egg-info/requires.txt
hhunt.egg-info/top_level.txt
hhunt/qt/__init__.py
hhunt/qt/main.py
hhunt/qt/widgets/__init__.py
hhunt/qt/widgets/mainwindow.py
hhunt/qt/widgets/tabs/__init__.py
hhunt/qt/widgets/tabs/apartment.py
hhunt/qt/widgets/tabs/house.py
hhunt/qt/widgets/tabs/websites.py